{
  "_class": "text",
  "attributedString": {
    "_class": "attributedString",
    "attributes": [
      {
        "_class": "stringAttribute",
        "attributes": {
          "MSAttributedStringColorAttribute": {
            "_class": "color",
            "alpha": 1,
            "blue": 1,
            "green": 1,
            "red": 1
          },
          "MSAttributedStringFontAttribute": {
            "_class": "fontDescriptor",
            "attributes": {
              "name": "Roboto-Regular",
              "size": 12
            }
          },
          "MSAttributedStringTextTransformAttribute": 1,
          "kerning": 0,
          "paragraphStyle": {
            "_class": "paragraphStyle",
            "alignment": 2,
            "allowsDefaultTighteningForTruncation": 0
          },
          "textStyleVerticalAlignmentKey": 0
        },
        "length": 6,
        "location": 0
      }
    ],
    "string": "CANCEL"
  },
  "automaticallyDrawOnUnderlyingPath": false,
  "booleanOperation": 0,
  "clippingMaskMode": 0,
  "do_objectID": "8DCFA7AF-0748-4C9F-9281-D79979CD223C",
  "dontSynchroniseWithSymbol": false,
  "exportOptions": {
    "_class": "exportOptions",
    "do_objectID": "2D86CB65-8EB1-432C-9041-870205E63D95",
    "exportFormats": [
    ],
    "includedLayerIds": [
    ],
    "layerOptions": 0,
    "shouldTrim": false
  },
  "frame": {
    "_class": "rect",
    "constrainProportions": false,
    "do_objectID": "1A60689C-86E3-4A93-B409-61B5D641AA7A",
    "height": 16,
    "width": 46,
    "x": 746,
    "y": 379
  },
  "glyphBounds": "{{0, 4}, {45, 10}}",
  "hasClippingMask": false,
  "isFixedToViewport": false,
  "isFlippedHorizontal": false,
  "isFlippedVertical": false,
  "isLocked": false,
  "isVisible": true,
  "layerListExpandedType": 0,
  "lineSpacingBehaviour": 2,
  "name": "Cancel",
  "nameIsFixed": true,
  "resizingConstraint": 36,
  "resizingType": 0,
  "rotation": 0,
  "shouldBreakMaskChain": false,
  "style": {
    "_class": "style",
    "endMarkerType": 0,
    "miterLimit": 10,
    "startMarkerType": 0,
    "textStyle": {
      "_class": "textStyle",
      "encodedAttributes": {
        "MSAttributedStringColorAttribute": {
          "_class": "color",
          "alpha": 1,
          "blue": 1,
          "green": 1,
          "red": 1
        },
        "MSAttributedStringFontAttribute": {
          "_class": "fontDescriptor",
          "attributes": {
            "name": "Roboto-Regular",
            "size": 12
          }
        },
        "MSAttributedStringTextTransformAttribute": 1,
        "kerning": 0,
        "paragraphStyle": {
          "_class": "paragraphStyle",
          "alignment": 2,
          "allowsDefaultTighteningForTruncation": 0
        },
        "textStyleVerticalAlignmentKey": 0
      },
      "verticalAlignment": 1
    },
    "windingRule": 1
  },
  "textBehaviour": 0
}