{
  "_class": "symbolInstance",
  "booleanOperation": 0,
  "clippingMaskMode": 0,
  "do_objectID": "1F73A59C-93ED-4DC2-A4A9-DE721D4D6269",
  "exportOptions": {
    "_class": "exportOptions",
    "do_objectID": "94903A8F-EBBD-41E1-BA3B-33278642D110",
    "exportFormats": [
    ],
    "includedLayerIds": [
    ],
    "layerOptions": 0,
    "shouldTrim": false
  },
  "frame": {
    "_class": "rect",
    "constrainProportions": false,
    "do_objectID": "75584BDB-24D0-476E-B7B7-304715388F00",
    "height": 99,
    "width": 218,
    "x": 391,
    "y": 26
  },
  "hasClippingMask": false,
  "horizontalSpacing": 0,
  "isFixedToViewport": false,
  "isFlippedHorizontal": false,
  "isFlippedVertical": false,
  "isLocked": false,
  "isVisible": true,
  "layerListExpandedType": 0,
  "name": "#2",
  "nameIsFixed": true,
  "overrideValues": [
    {
      "_class": "overrideValue",
      "do_objectID": "5AEE9375-EE61-4BB3-AA67-1FA624934E47",
      "overrideName": "DF7CA482-BAE3-4E9E-9337-46C0994A2B3C_symbolID",
      "value": "FBB78B6D-9B10-4847-B919-A29A7EE074E1"
    },
    {
      "_class": "overrideValue",
      "do_objectID": "D94CB140-A6D1-4365-B1BB-1E9BF01085C0",
      "overrideName": "020E373E-F2D9-47BA-AEC7-8539C6D4C2AE_symbolID",
      "value": "D97135EC-C9A6-43EF-95F5-0F622670F560"
    },
    {
      "_class": "overrideValue",
      "do_objectID": "BFEC5663-7ECD-46E8-B25E-1AC4BB77E40E",
      "overrideName": "D3C34F91-60A0-4117-82AD-746D58D7CE11_stringValue",
      "value": "Camera"
    }
  ],
  "resizingConstraint": 63,
  "resizingType": 0,
  "rotation": 0,
  "scale": 1,
  "shouldBreakMaskChain": false,
  "style": {
    "_class": "style",
    "do_objectID": "CD0995C6-2E71-4AEE-8F3D-BADB83103AAB",
    "endMarkerType": 0,
    "miterLimit": 10,
    "startMarkerType": 0,
    "windingRule": 1
  },
  "symbolID": "6F5DC9AE-EECB-415D-BAA6-F13D5F2BD971",
  "userInfo": {
    "com.animaapp.stc-sketch-plugin": {
      "kModelPropertiesKey": {
      }
    }
  },
  "verticalSpacing": 0
}