{
  "_class": "shapePath",
  "booleanOperation": 0,
  "clippingMaskMode": 0,
  "do_objectID": "BA7C9AE6-542C-4AEA-B673-9583901833E7",
  "edited": true,
  "exportOptions": {
    "_class": "exportOptions",
    "do_objectID": "881DA7A2-1B66-4406-8A9D-52A352BBB336",
    "exportFormats": [
    ],
    "includedLayerIds": [
    ],
    "layerOptions": 0,
    "shouldTrim": false
  },
  "frame": {
    "_class": "rect",
    "constrainProportions": false,
    "do_objectID": "0439E5C7-C98D-4A7A-84FA-4542E3D28DFD",
    "height": 41.05940594059409,
    "width": 36.00000000000001,
    "x": 0,
    "y": 0
  },
  "hasClippingMask": false,
  "isClosed": true,
  "isFixedToViewport": false,
  "isFlippedHorizontal": false,
  "isFlippedVertical": false,
  "isLocked": false,
  "isVisible": true,
  "layerListExpandedType": 0,
  "name": "Shape",
  "nameIsFixed": false,
  "pointRadiusBehaviour": 1,
  "points": [
    {
      "_class": "curvePoint",
      "cornerRadius": 0,
      "curveFrom": "{0, 0.53374651776947679}",
      "curveMode": 3,
      "curveTo": "{0, 0.19565501533152338}",
      "hasCurveFrom": true,
      "hasCurveTo": true,
      "point": "{0, 0.43609228624310475}"
    },
    {
      "_class": "curvePoint",
      "cornerRadius": 0,
      "curveFrom": "{0.10497862861958937, 0.7034801227539097}",
      "curveMode": 3,
      "curveTo": "{0.036180844019023543, 0.62607994663176003}",
      "hasCurveFrom": true,
      "hasCurveTo": true,
      "point": "{0.10465354283306241, 0.70310906677865082}"
    },
    {
      "_class": "curvePoint",
      "cornerRadius": 0,
      "curveFrom": "{0.24848995645455824, 0.87710631495049185}",
      "curveMode": 4,
      "curveTo": "{0.10533983504906383, 0.70384767820110006}",
      "hasCurveFrom": true,
      "hasCurveTo": true,
      "point": "{0.10569702807376634, 0.70421873417635883}"
    },
    {
      "_class": "curvePoint",
      "cornerRadius": 0,
      "curveFrom": "{0.20536190877530949, 0.97370688752825152}",
      "curveMode": 4,
      "curveTo": "{0.21299540465153605, 0.95934072033521156}",
      "hasCurveFrom": true,
      "hasCurveTo": true,
      "point": "{0.21299540465153605, 0.95948074145795081}"
    },
    {
      "_class": "curvePoint",
      "cornerRadius": 0,
      "curveFrom": "{0.23319085746392948, 0.99914522500189162}",
      "curveMode": 3,
      "curveTo": "{0.2124094475548331, 0.99063894179548673}",
      "hasCurveFrom": true,
      "hasCurveTo": true,
      "point": "{0.22871992454799023, 0.99732495040628233}"
    },
    {
      "_class": "curvePoint",
      "cornerRadius": 0,
      "curveFrom": "{0.25478297513695736, 0.99999935385060068}",
      "curveMode": 2,
      "curveTo": "{0.23788654104709722, 1.0000273580751484}",
      "hasCurveFrom": true,
      "hasCurveTo": true,
      "point": "{0.24251801015391397, 0.99999935385060068}"
    },
    {
      "_class": "curvePoint",
      "cornerRadius": 0,
      "curveFrom": "{0.27797644131398863, 0.97268473333225536}",
      "curveMode": 2,
      "curveTo": "{0.26653021090442069, 0.99393993976406281}",
      "hasCurveFrom": true,
      "hasCurveTo": true,
      "point": "{0.27207272289446743, 0.98360988143397976}"
    },
    {
      "_class": "curvePoint",
      "cornerRadius": 0,
      "curveFrom": "{0.15616157967611813, 0.66799526972373302}",
      "curveMode": 4,
      "curveTo": "{0.32462825838299914, 0.87084387023598187}",
      "hasCurveFrom": true,
      "hasCurveTo": true,
      "point": "{0.15691208636847062, 0.66887740279698982}"
    },
    {
      "_class": "curvePoint",
      "cornerRadius": 0,
      "curveFrom": "{0.096137097907009347, 0.59976297661293121}",
      "curveMode": 4,
      "curveTo": "{0.15541107298376575, 0.66714114087502407}",
      "hasCurveFrom": true,
      "hasCurveTo": true,
      "point": "{0.15456424457688672, 0.66634652100347913}"
    },
    {
      "_class": "curvePoint",
      "cornerRadius": 0,
      "curveFrom": "{0.065274015210803962, 0.22698124101634612}",
      "curveMode": 3,
      "curveTo": "{0.065274015210803962, 0.52020647520059793}",
      "hasCurveFrom": true,
      "hasCurveTo": true,
      "point": "{0.065274015210803962, 0.43606428201855679}"
    },
    {
      "_class": "curvePoint",
      "cornerRadius": 0,
      "curveFrom": "{0.73969056649208365, 0.056883581112791355}",
      "curveMode": 2,
      "curveTo": "{0.260329500531776, 0.056883581112791355}",
      "hasCurveFrom": true,
      "hasCurveTo": true,
      "point": "{0.50001003351192985, 0.056883581112791355}"
    },
    {
      "_class": "curvePoint",
      "cornerRadius": 0,
      "curveFrom": "{0.93475407862259963, 0.52043050899698073}",
      "curveMode": 3,
      "curveTo": "{0.93475407862259963, 0.2269812410163462}",
      "hasCurveFrom": true,
      "hasCurveTo": true,
      "point": "{0.93475407862259963, 0.4360642820185569}"
    },
    {
      "_class": "curvePoint",
      "cornerRadius": 0,
      "curveFrom": "{0.67654365581040699, 0.86973420283827407}",
      "curveMode": 4,
      "curveTo": "{0.90369835249734132, 0.60030205793547697}",
      "hasCurveFrom": true,
      "hasCurveTo": true,
      "point": "{0.84435614953946203, 0.66762421374847436}"
    },
    {
      "_class": "curvePoint",
      "cornerRadius": 0,
      "curveFrom": "{0.7388196576565732, 0.99775201483063714}",
      "curveMode": 2,
      "curveTo": "{0.72508578652700029, 0.97274074178135106}",
      "hasCurveFrom": true,
      "hasCurveTo": true,
      "point": "{0.73115405454217097, 0.98383741575843109}"
    },
    {
      "_class": "curvePoint",
      "cornerRadius": 0,
      "curveFrom": "{0.7898781931651716, 0.9908629755918692}",
      "curveMode": 2,
      "curveTo": "{0.75764252603696369, 1.0034438734699846}",
      "hasCurveFrom": true,
      "hasCurveTo": true,
      "point": "{0.77376035960106759, 0.99715342453092692}"
    },
    {
      "_class": "curvePoint",
      "cornerRadius": 0,
      "curveFrom": "{0.7899705014749262, 0.95908168125814419}",
      "curveMode": 3,
      "curveTo": "{0.79718258985009938, 0.97413395195260588}",
      "hasCurveFrom": true,
      "hasCurveTo": true,
      "point": "{0.79036381514257625, 0.9599078058823054}"
    },
    {
      "_class": "curvePoint",
      "cornerRadius": 0,
      "curveFrom": "{0.96424457688680199, 0.62494227500950417}",
      "curveMode": 4,
      "curveTo": "{0.75258563602432127, 0.87519852715317048}",
      "hasCurveFrom": true,
      "hasCurveTo": true,
      "point": "{0.89665081371781763, 0.70165634763023177}"
    },
    {
      "_class": "curvePoint",
      "cornerRadius": 0,
      "curveFrom": "{1, 0.19562351057890712}",
      "curveMode": 3,
      "curveTo": "{1, 0.53311992324521906}",
      "hasCurveFrom": true,
      "hasCurveTo": true,
      "point": "{1, 0.43609228624310475}"
    },
    {
      "_class": "curvePoint",
      "cornerRadius": 0,
      "curveFrom": "{0.22431320610840194, 0}",
      "curveMode": 2,
      "curveTo": "{0.77571488772500141, 0}",
      "hasCurveFrom": true,
      "hasCurveTo": true,
      "point": "{0.5000140469167017, 0}"
    }
  ],
  "resizingConstraint": 63,
  "resizingType": 0,
  "rotation": 0,
  "shouldBreakMaskChain": false,
  "style": {
    "_class": "style",
    "endMarkerType": 0,
    "fills": [
      {
        "_class": "fill",
        "color": {
          "_class": "color",
          "alpha": 1,
          "blue": 1,
          "green": 1,
          "red": 1
        },
        "fillType": 0,
        "isEnabled": true,
        "noiseIndex": 0,
        "noiseIntensity": 0,
        "patternFillType": 1,
        "patternTileScale": 1
      }
    ],
    "miterLimit": 10,
    "startMarkerType": 0,
    "windingRule": 0
  }
}