{
  "_class": "text",
  "attributedString": {
    "_class": "attributedString",
    "attributes": [
      {
        "_class": "stringAttribute",
        "attributes": {
          "MSAttributedStringColorAttribute": {
            "_class": "color",
            "alpha": 1,
            "blue": 1,
            "green": 1,
            "red": 1
          },
          "MSAttributedStringFontAttribute": {
            "_class": "fontDescriptor",
            "attributes": {
              "name": "Roboto-Regular",
              "size": 12
            }
          },
          "kerning": 0,
          "paragraphStyle": {
            "_class": "paragraphStyle",
            "alignment": 0,
            "allowsDefaultTighteningForTruncation": 0
          }
        },
        "length": 94,
        "location": 0
      }
    ],
    "string": "Brief description of lorem ipsum dolor sit amet, consectetur adipisicing elit, sed do eiusmod."
  },
  "automaticallyDrawOnUnderlyingPath": false,
  "booleanOperation": 0,
  "clippingMaskMode": 0,
  "do_objectID": "5FEE391D-5887-4F53-AE22-140685155308",
  "dontSynchroniseWithSymbol": false,
  "exportOptions": {
    "_class": "exportOptions",
    "do_objectID": "06D8484E-C33A-4740-97D4-E7E869435EFB",
    "exportFormats": [
    ],
    "includedLayerIds": [
    ],
    "layerOptions": 0,
    "shouldTrim": false
  },
  "frame": {
    "_class": "rect",
    "constrainProportions": false,
    "do_objectID": "3ED5FAD8-12F6-4A2B-B6AB-1E416A6293A1",
    "height": 39,
    "width": 260,
    "x": 94,
    "y": 73
  },
  "glyphBounds": "{{0, 3}, {253, 29}}",
  "hasClippingMask": false,
  "isFixedToViewport": false,
  "isFlippedHorizontal": false,
  "isFlippedVertical": false,
  "isLocked": false,
  "isVisible": true,
  "layerListExpandedType": 0,
  "lineSpacingBehaviour": 2,
  "name": "Description",
  "nameIsFixed": true,
  "resizingConstraint": 63,
  "resizingType": 0,
  "rotation": 0,
  "sharedStyleID": "052FBDBD-07D8-43DA-96C7-79094B24991B",
  "shouldBreakMaskChain": false,
  "style": {
    "_class": "style",
    "blur": {
      "_class": "blur",
      "center": "{0.5, 0.5}",
      "do_objectID": "40865837-84A2-4A07-AACC-8821D7E5A114",
      "isEnabled": false,
      "motionAngle": 0,
      "radius": 5,
      "saturation": 1,
      "type": 0
    },
    "do_objectID": "B7E57726-BC42-4ED8-8338-534214ADB8B8",
    "endMarkerType": 0,
    "miterLimit": 10,
    "startMarkerType": 0,
    "textStyle": {
      "_class": "textStyle",
      "do_objectID": "85F31EB3-40DA-418B-B8E9-690AF19C9313",
      "encodedAttributes": {
        "MSAttributedStringColorAttribute": {
          "_class": "color",
          "alpha": 1,
          "blue": 1,
          "green": 1,
          "red": 1
        },
        "MSAttributedStringFontAttribute": {
          "_class": "fontDescriptor",
          "attributes": {
            "name": "Roboto-Regular",
            "size": 12
          }
        },
        "kerning": 0,
        "paragraphStyle": {
          "_class": "paragraphStyle",
          "alignment": 0,
          "allowsDefaultTighteningForTruncation": 0
        }
      },
      "verticalAlignment": 0
    },
    "windingRule": 1
  },
  "textBehaviour": 2
}