{
  "_class": "symbolInstance",
  "booleanOperation": 0,
  "clippingMaskMode": 0,
  "do_objectID": "9E636ACB-634F-4684-9B78-9D86D5E7F78B",
  "exportOptions": {
    "_class": "exportOptions",
    "do_objectID": "5CA1CF6C-D8ED-43C7-B191-16F12752058D",
    "exportFormats": [
    ],
    "includedLayerIds": [
    ],
    "layerOptions": 0,
    "shouldTrim": false
  },
  "frame": {
    "_class": "rect",
    "constrainProportions": false,
    "do_objectID": "80CD8F54-8142-4D0F-8A5D-36E61754A28C",
    "height": 901,
    "width": 1440,
    "x": 0,
    "y": 0
  },
  "hasClippingMask": false,
  "horizontalSpacing": 0,
  "isFixedToViewport": false,
  "isFlippedHorizontal": false,
  "isFlippedVertical": false,
  "isLocked": false,
  "isVisible": true,
  "layerListExpandedType": 0,
  "name": "Background",
  "nameIsFixed": true,
  "overrideValues": [
  ],
  "resizingConstraint": 63,
  "resizingType": 0,
  "rotation": 0,
  "scale": 1,
  "shouldBreakMaskChain": false,
  "style": {
    "_class": "style",
    "contextSettings": {
      "_class": "graphicsContextSettings",
      "blendMode": 0,
      "do_objectID": "05D1A2BD-C69C-4C1A-859E-0C6159D50FE0",
      "opacity": 0.800000011920929
    },
    "do_objectID": "DE49D7D2-0BFC-4F03-9BA1-AB41790BB863",
    "endMarkerType": 0,
    "miterLimit": 10,
    "startMarkerType": 0,
    "windingRule": 1
  },
  "symbolID": "EA93CD7F-9CE2-48E2-BE75-1407CEE6C651",
  "verticalSpacing": 0
}