{
  "_class": "symbolInstance",
  "booleanOperation": -1,
  "clippingMaskMode": 0,
  "do_objectID": "EA770D6D-5609-4F9E-BAB6-A26378F29F1F",
  "exportOptions": {
    "_class": "exportOptions",
    "do_objectID": "B3EDD777-F98B-4FEF-978D-B97BCC50C3B2",
    "exportFormats": [
    ],
    "includedLayerIds": [
    ],
    "layerOptions": 0,
    "shouldTrim": false
  },
  "frame": {
    "_class": "rect",
    "constrainProportions": false,
    "do_objectID": "CC3A17E6-A3B1-4442-9779-2F5C7E1882BD",
    "height": 110,
    "width": 160,
    "x": 90,
    "y": 3445
  },
  "hasClippingMask": false,
  "horizontalSpacing": 0,
  "isFixedToViewport": false,
  "isFlippedHorizontal": false,
  "isFlippedVertical": false,
  "isLocked": false,
  "isVisible": true,
  "layerListExpandedType": 0,
  "name": "Molecules / Layouts / #1",
  "nameIsFixed": false,
  "overrideValues": [
  ],
  "resizingConstraint": 63,
  "resizingType": 0,
  "rotation": 0,
  "scale": 1,
  "shouldBreakMaskChain": false,
  "style": {
    "_class": "style",
    "do_objectID": "A1D5DF19-C95B-46E4-B3DD-C819AA111A0F",
    "endMarkerType": 0,
    "miterLimit": 10,
    "startMarkerType": 0,
    "windingRule": 1
  },
  "symbolID": "1E471446-A156-4856-9A35-D314C81D926C",
  "verticalSpacing": 0
}