{
  "_class": "symbolMaster",
  "allowsOverrides": true,
  "backgroundColor": {
    "_class": "color",
    "alpha": 1,
    "blue": 0.4196078431372549,
    "green": 0.3333333333333334,
    "red": 0.2666666666666667
  },
  "booleanOperation": 0,
  "changeIdentifier": 2081,
  "clippingMaskMode": 0,
  "do_objectID": "26921BED-39C2-4479-BA3B-DC01DCC8148C",
  "exportOptions": {
    "_class": "exportOptions",
    "do_objectID": "E877F1B7-73DF-4013-B3D0-A5405923EE37",
    "exportFormats": [
      {
        "_class": "exportFormat",
        "absoluteSize": 0,
        "fileFormat": "jpg",
        "name": "",
        "namingScheme": 0,
        "scale": 1,
        "visibleScaleType": 0
      }
    ],
    "includedLayerIds": [
    ],
    "layerOptions": 0,
    "shouldTrim": false
  },
  "frame": {
    "_class": "rect",
    "constrainProportions": false,
    "do_objectID": "2395975C-52A4-4915-B834-6741B14C94BC",
    "height": 100,
    "width": 100,
    "x": 674,
    "y": 1800
  },
  "groupLayout": {
    "_class": "MSImmutableFreeformGroupLayout"
  },
  "hasBackgroundColor": true,
  "hasClickThrough": true,
  "hasClippingMask": false,
  "horizontalRulerData": {
    "_class": "rulerData",
    "base": 0,
    "do_objectID": "AE9F8A75-7D4A-4221-88B0-27C120014631",
    "guides": [
    ]
  },
  "includeBackgroundColorInExport": true,
  "includeBackgroundColorInInstance": false,
  "includeInCloudUpload": true,
  "isFixedToViewport": false,
  "isFlippedHorizontal": false,
  "isFlippedVertical": false,
  "isFlowHome": false,
  "isLocked": false,
  "isVisible": true,
  "layerListExpandedType": 0,
  "layers": [
    {
      "class": "rectangle",
      "id": "4C4A31DF-0107-4208-A02C-DC78F1CAB2D1"
    },
    {
      "class": "group",
      "id": "402C89A9-1359-4263-85C3-3A7C31390020"
    }
  ],
  "name": "Atoms / icons /illustrated/ Speaker_White",
  "nameIsFixed": true,
  "overrideProperties": [
    {
      "_class": "MSImmutableOverrideProperty",
      "canOverride": true,
      "overrideName": "FC3B8E0E-C387-4980-9AF7-46BAF212FEDE_image"
    },
    {
      "_class": "MSImmutableOverrideProperty",
      "canOverride": true,
      "overrideName": "74682758-5AD6-41D0-B7BD-3F4040A789E3_layerStyle"
    },
    {
      "_class": "MSImmutableOverrideProperty",
      "canOverride": true,
      "overrideName": "192DDBF2-B783-46D0-9ED9-C00EC2AB83BB_image"
    },
    {
      "_class": "MSImmutableOverrideProperty",
      "canOverride": true,
      "overrideName": "192DDBF2-B783-46D0-9ED9-C00EC2AB83BB_layerStyle"
    },
    {
      "_class": "MSImmutableOverrideProperty",
      "canOverride": true,
      "overrideName": "9165502A-2FDC-495F-94B6-5975413213F9_layerStyle"
    },
    {
      "_class": "MSImmutableOverrideProperty",
      "canOverride": true,
      "overrideName": "74682758-5AD6-41D0-B7BD-3F4040A789E3_image"
    },
    {
      "_class": "MSImmutableOverrideProperty",
      "canOverride": true,
      "overrideName": "FC3B8E0E-C387-4980-9AF7-46BAF212FEDE_layerStyle"
    },
    {
      "_class": "MSImmutableOverrideProperty",
      "canOverride": true,
      "overrideName": "9165502A-2FDC-495F-94B6-5975413213F9_image"
    }
  ],
  "resizesContent": false,
  "resizingConstraint": 63,
  "resizingType": 0,
  "rotation": 0,
  "shouldBreakMaskChain": true,
  "style": {
    "_class": "style",
    "do_objectID": "83213ADA-839E-4B4C-B650-B60F399E7979",
    "endMarkerType": 0,
    "fills": [
      {
        "_class": "fill",
        "color": {
          "_class": "color",
          "alpha": 1,
          "blue": 1,
          "green": 1,
          "red": 1
        },
        "fillType": 0,
        "isEnabled": true,
        "noiseIndex": 0,
        "noiseIntensity": 0,
        "patternFillType": 1,
        "patternTileScale": 1
      }
    ],
    "miterLimit": 10,
    "startMarkerType": 0,
    "windingRule": 1
  },
  "symbolID": "FC09C010-7F6B-4DFD-A018-6252E30FE330",
  "userInfo": {
    "com.animaapp.stc-sketch-plugin": {
      "kModelPropertiesKey": {
      }
    }
  },
  "verticalRulerData": {
    "_class": "rulerData",
    "base": 0,
    "do_objectID": "669B38C4-CB96-4CFB-81BD-05029CD20FC7",
    "guides": [
    ]
  }
}