{
  "_class": "group",
  "booleanOperation": -1,
  "clippingMaskMode": 0,
  "do_objectID": "30285952-FDF2-435D-91FE-2E612776A5D6",
  "exportOptions": {
    "_class": "exportOptions",
    "do_objectID": "E48AA858-D691-47EE-99D6-B869A1A740C9",
    "exportFormats": [
    ],
    "includedLayerIds": [
    ],
    "layerOptions": 0,
    "shouldTrim": false
  },
  "frame": {
    "_class": "rect",
    "constrainProportions": false,
    "do_objectID": "91397233-43AA-4154-8790-5AFD36CD7D81",
    "height": 90.13333333333333,
    "width": 178.2857142857143,
    "x": 13.86666666666667,
    "y": 54.47619047619047
  },
  "groupLayout": {
    "_class": "MSImmutableFreeformGroupLayout"
  },
  "hasClickThrough": false,
  "hasClippingMask": false,
  "isFixedToViewport": false,
  "isFlippedHorizontal": false,
  "isFlippedVertical": false,
  "isLocked": false,
  "isVisible": true,
  "layerListExpandedType": 0,
  "layers": [
    {
      "class": "symbolInstance",
      "id": "FC94A8EB-178A-4AFE-9CA5-8E923B9D180E"
    },
    {
      "class": "symbolInstance",
      "id": "F172D413-6833-42DA-B606-264A8963C60F"
    },
    {
      "class": "symbolInstance",
      "id": "6426C791-12D0-4495-AFFF-772B3B32DAFD"
    },
    {
      "class": "symbolInstance",
      "id": "49F7F983-8638-40AE-8B7E-31EF5EBC6770"
    },
    {
      "class": "symbolInstance",
      "id": "C9249A7E-E4B4-4BA5-A42B-67FFADACAF33"
    },
    {
      "class": "symbolInstance",
      "id": "A161DE87-76A9-4718-A6D7-6D3B6A389B8D"
    },
    {
      "class": "symbolInstance",
      "id": "E3726923-8E2A-4D56-971F-5DD544148D2D"
    }
  ],
  "name": "Bars",
  "nameIsFixed": true,
  "resizingConstraint": 63,
  "resizingType": 0,
  "rotation": 0,
  "shouldBreakMaskChain": false,
  "style": {
    "_class": "style",
    "do_objectID": "52126292-4E04-4381-80B3-7FAC525A00B8",
    "endMarkerType": 0,
    "miterLimit": 10,
    "startMarkerType": 0,
    "windingRule": 1
  }
}