{
  "_class": "shapePath",
  "booleanOperation": -1,
  "clippingMaskMode": 0,
  "do_objectID": "DC4C03E2-4AB0-4FD8-A0D8-647F7B5CCD64",
  "edited": true,
  "exportOptions": {
    "_class": "exportOptions",
    "do_objectID": "9012A1F2-6080-4100-B8CE-19ACAC38D167",
    "exportFormats": [
    ],
    "includedLayerIds": [
    ],
    "layerOptions": 0,
    "shouldTrim": false
  },
  "frame": {
    "_class": "rect",
    "constrainProportions": false,
    "do_objectID": "AC48AE2C-F34E-4E81-A9BC-DCA1478DD1DA",
    "height": 22.96551724137931,
    "width": 2.551724137931032,
    "x": 53.58620689655173,
    "y": 35.72413793103448
  },
  "hasClippingMask": false,
  "isClosed": true,
  "isFixedToViewport": false,
  "isFlippedHorizontal": false,
  "isFlippedVertical": false,
  "isLocked": false,
  "isVisible": true,
  "layerListExpandedType": 0,
  "name": "Path",
  "nameIsFixed": false,
  "pointRadiusBehaviour": 1,
  "points": [
    {
      "_class": "curvePoint",
      "cornerRadius": 0,
      "curveFrom": "{0.77700000000000102, 0}",
      "curveMode": 2,
      "curveTo": "{0.22299999999999898, 0}",
      "hasCurveFrom": true,
      "hasCurveTo": true,
      "point": "{0.5, 0}"
    },
    {
      "_class": "curvePoint",
      "cornerRadius": 0,
      "curveFrom": "{1, 0.055555555555555552}",
      "curveMode": 4,
      "curveTo": "{1, 0.02477777777777786}",
      "hasCurveFrom": false,
      "hasCurveTo": true,
      "point": "{1, 0.055555555555555552}"
    },
    {
      "_class": "curvePoint",
      "cornerRadius": 0,
      "curveFrom": "{1, 0.97522222222222232}",
      "curveMode": 4,
      "curveTo": "{1, 0.94444444444444442}",
      "hasCurveFrom": true,
      "hasCurveTo": false,
      "point": "{1, 0.94444444444444442}"
    },
    {
      "_class": "curvePoint",
      "cornerRadius": 0,
      "curveFrom": "{0.22299999999999898, 1}",
      "curveMode": 2,
      "curveTo": "{0.77700000000000102, 1}",
      "hasCurveFrom": true,
      "hasCurveTo": true,
      "point": "{0.5, 1}"
    },
    {
      "_class": "curvePoint",
      "cornerRadius": 0,
      "curveFrom": "{0, 0.94444444444444442}",
      "curveMode": 4,
      "curveTo": "{0, 0.97522222222222232}",
      "hasCurveFrom": false,
      "hasCurveTo": true,
      "point": "{0, 0.94444444444444442}"
    },
    {
      "_class": "curvePoint",
      "cornerRadius": 0,
      "curveFrom": "{0, 0.02477777777777786}",
      "curveMode": 4,
      "curveTo": "{0, 0.055555555555555552}",
      "hasCurveFrom": true,
      "hasCurveTo": false,
      "point": "{0, 0.055555555555555552}"
    }
  ],
  "resizingConstraint": 63,
  "resizingType": 0,
  "rotation": 0,
  "shouldBreakMaskChain": false,
  "style": {
    "_class": "style",
    "endMarkerType": 0,
    "fills": [
      {
        "_class": "fill",
        "color": {
          "_class": "color",
          "alpha": 1,
          "blue": 1,
          "green": 1,
          "red": 1
        },
        "fillType": 0,
        "isEnabled": true,
        "noiseIndex": 0,
        "noiseIntensity": 0,
        "patternFillType": 1,
        "patternTileScale": 1
      }
    ],
    "miterLimit": 10,
    "startMarkerType": 0,
    "windingRule": 0
  },
  "userInfo": {
    "com.animaapp.stc-sketch-plugin": {
      "kModelPropertiesKey": {
      }
    }
  }
}