{
  "_class": "rectangle",
  "booleanOperation": -1,
  "clippingMaskMode": 0,
  "do_objectID": "EE80D123-D77F-4D21-9EDF-28E61C1A51C6",
  "edited": false,
  "exportOptions": {
    "_class": "exportOptions",
    "do_objectID": "47ED8F14-C41D-442B-B65D-2F5F11B2FC33",
    "exportFormats": [
    ],
    "includedLayerIds": [
    ],
    "layerOptions": 0,
    "shouldTrim": false
  },
  "fixedRadius": 0,
  "frame": {
    "_class": "rect",
    "constrainProportions": true,
    "do_objectID": "8376BF48-D2F8-4661-BFD6-E9478CA23635",
    "height": 19.55422390271414,
    "width": 19.55422390271414,
    "x": 4.190190836294464,
    "y": 4.190190836295374
  },
  "hasClippingMask": true,
  "hasConvertedToNewRoundCorners": true,
  "isClosed": true,
  "isFixedToViewport": false,
  "isFlippedHorizontal": false,
  "isFlippedVertical": false,
  "isLocked": false,
  "isVisible": true,
  "layerListExpandedType": 0,
  "name": "Mask",
  "nameIsFixed": false,
  "pointRadiusBehaviour": 1,
  "points": [
    {
      "_class": "curvePoint",
      "cornerRadius": 0,
      "curveFrom": "{0, 1.110223024625156e-16}",
      "curveMode": 1,
      "curveTo": "{0, 1.110223024625156e-16}",
      "hasCurveFrom": false,
      "hasCurveTo": false,
      "point": "{0, 1.110223024625156e-16}"
    },
    {
      "_class": "curvePoint",
      "cornerRadius": 0,
      "curveFrom": "{0.99999999999999956, 1.110223024625156e-16}",
      "curveMode": 1,
      "curveTo": "{0.99999999999999956, 1.110223024625156e-16}",
      "hasCurveFrom": false,
      "hasCurveTo": false,
      "point": "{0.99999999999999956, 1.110223024625156e-16}"
    },
    {
      "_class": "curvePoint",
      "cornerRadius": 0,
      "curveFrom": "{0.99999999999999956, 0.99999999999999967}",
      "curveMode": 1,
      "curveTo": "{0.99999999999999956, 0.99999999999999967}",
      "hasCurveFrom": false,
      "hasCurveTo": false,
      "point": "{0.99999999999999956, 0.99999999999999967}"
    },
    {
      "_class": "curvePoint",
      "cornerRadius": 0,
      "curveFrom": "{0, 0.99999999999999967}",
      "curveMode": 1,
      "curveTo": "{0, 0.99999999999999967}",
      "hasCurveFrom": false,
      "hasCurveTo": false,
      "point": "{0, 0.99999999999999967}"
    }
  ],
  "resizingConstraint": 63,
  "resizingType": 0,
  "rotation": 315,
  "shouldBreakMaskChain": false,
  "style": {
    "_class": "style",
    "borders": [
      {
        "_class": "border",
        "color": {
          "_class": "color",
          "alpha": 1,
          "blue": 0.592,
          "green": 0.592,
          "red": 0.592
        },
        "fillType": 0,
        "isEnabled": false,
        "position": 1,
        "thickness": 1
      }
    ],
    "do_objectID": "4FAA1202-DE59-42B9-82E1-9F4142535FD0",
    "endMarkerType": 0,
    "fills": [
      {
        "_class": "fill",
        "color": {
          "_class": "color",
          "alpha": 1,
          "blue": 0.847,
          "green": 0.847,
          "red": 0.847
        },
        "fillType": 0,
        "isEnabled": false,
        "noiseIndex": 0,
        "noiseIntensity": 0,
        "patternFillType": 1,
        "patternTileScale": 1
      }
    ],
    "miterLimit": 10,
    "startMarkerType": 0,
    "windingRule": 1
  },
  "userInfo": {
    "com.animaapp.stc-sketch-plugin": {
      "kModelPropertiesKey": {
        "constraints": {
          "aspectRatio": {
            "constant": 14,
            "enabled": 1,
            "modelID": "constraint_02eba78c-2fe0-4a38-9318-ff42e0b47f38",
            "model_class": "ADModelConstraint",
            "model_version": 0.1,
            "multiplier": 14
          },
          "automatic": 1,
          "modelID": "viewConstraints_08032e21-aa14-4341-99d6-940f1d7020ee",
          "model_class": "ADModelViewConstraints",
          "model_version": 0.1,
          "scaleFactor": 1
        }
      }
    }
  }
}