{
  "_class": "group",
  "booleanOperation": 0,
  "clippingMaskMode": 0,
  "do_objectID": "FDE52999-AE3E-4D8C-A185-486DB29E36DC",
  "exportOptions": {
    "_class": "exportOptions",
    "do_objectID": "B755A218-7F0E-4EF0-A441-294220BF1EC7",
    "exportFormats": [
    ],
    "includedLayerIds": [
    ],
    "layerOptions": 0,
    "shouldTrim": false
  },
  "frame": {
    "_class": "rect",
    "constrainProportions": false,
    "do_objectID": "F271B84D-BD63-4EEC-B5E8-6AC7E994F4F8",
    "height": 35,
    "width": 156,
    "x": 693,
    "y": 93
  },
  "groupLayout": {
    "_class": "MSImmutableFreeformGroupLayout"
  },
  "hasClickThrough": false,
  "hasClippingMask": false,
  "isFixedToViewport": false,
  "isFlippedHorizontal": false,
  "isFlippedVertical": false,
  "isLocked": false,
  "isVisible": true,
  "layerListExpandedType": 0,
  "layers": [
    {
      "class": "oval",
      "id": "430DB244-125C-4517-9C50-4BF51BA236C1"
    },
    {
      "class": "symbolInstance",
      "id": "CFC8547D-2050-4741-9AC4-4C2C9CE9268E"
    },
    {
      "class": "symbolInstance",
      "id": "92A61F58-17B8-4F7D-B7A5-3ED41D73BEDE"
    }
  ],
  "name": "Hover",
  "nameIsFixed": true,
  "resizingConstraint": 63,
  "resizingType": 0,
  "rotation": 0,
  "shouldBreakMaskChain": false,
  "style": {
    "_class": "style",
    "do_objectID": "B16E2D1E-3B84-4FF5-9898-C3D6B0402A26",
    "endMarkerType": 0,
    "miterLimit": 10,
    "startMarkerType": 0,
    "windingRule": 1
  }
}